odoo10_addon_l10n_ch_bank_statement_import_postfinance-10.0.1.0.4-nspkg.pth
odoo/addons/l10n_ch_bank_statement_import_postfinance/README.rst
odoo/addons/l10n_ch_bank_statement_import_postfinance/__init__.py
odoo/addons/l10n_ch_bank_statement_import_postfinance/__manifest__.py
odoo/addons/l10n_ch_bank_statement_import_postfinance/i18n/l10n_ch_bank_statement_import_postfinance.pot
odoo/addons/l10n_ch_bank_statement_import_postfinance/migrations/9.0.1.0.0/post-migration.py
odoo/addons/l10n_ch_bank_statement_import_postfinance/models/__init__.py
odoo/addons/l10n_ch_bank_statement_import_postfinance/models/account_bank_statement_line.py
odoo/addons/l10n_ch_bank_statement_import_postfinance/models/postfinance_file_parser.py
odoo/addons/l10n_ch_bank_statement_import_postfinance/static/description/icon.png
odoo/addons/l10n_ch_bank_statement_import_postfinance/static/src/js/account_statement_reconciliation.js
odoo/addons/l10n_ch_bank_statement_import_postfinance/static/src/xml/l10n_ch_statement_line_layout.xml
odoo/addons/l10n_ch_bank_statement_import_postfinance/test_files/demo_pf_ch.tar.gz
odoo/addons/l10n_ch_bank_statement_import_postfinance/tests/__init__.py
odoo/addons/l10n_ch_bank_statement_import_postfinance/tests/test_postfinance_xml.py
odoo/addons/l10n_ch_bank_statement_import_postfinance/views/account_bank_statement_import_postfinance_view.xml
odoo/addons/l10n_ch_bank_statement_import_postfinance/views/l10n_ch_account_statement_base_import.xml
odoo/addons/l10n_ch_bank_statement_import_postfinance/views/statement_line_view.xml
odoo/addons/l10n_ch_bank_statement_import_postfinance/wizards/__init__.py
odoo/addons/l10n_ch_bank_statement_import_postfinance/wizards/account_bank_statement_import_postfinance.py
odoo10_addon_l10n_ch_bank_statement_import_postfinance-10.0.1.0.4.dist-info/METADATA
odoo10_addon_l10n_ch_bank_statement_import_postfinance-10.0.1.0.4.dist-info/WHEEL
odoo10_addon_l10n_ch_bank_statement_import_postfinance-10.0.1.0.4.dist-info/namespace_packages.txt
odoo10_addon_l10n_ch_bank_statement_import_postfinance-10.0.1.0.4.dist-info/top_level.txt
odoo10_addon_l10n_ch_bank_statement_import_postfinance-10.0.1.0.4.dist-info/RECORD
